{
  "groups": [],
  "properties": [

    {
      "name": "spring.ai.alibaba.mcp.nacos.registry.service-register",
      "type": "java.lang.String",
      "description": "if register mcp server service to nacos.",
      "defaultValue": ""
    },
    {
      "name": "spring.ai.alibaba.mcp.nacos.registry.service-namespace",
      "type": "java.lang.String",
      "description": "Namespace for mcp server service.",
      "defaultValue": ""
    },
    {
      "name": "spring.ai.alibaba.mcp.nacos.registry.service-group",
      "type": "java.lang.String",
      "description": "Group for mcp server service.",
      "defaultValue": "DEFAULT_GROUP"
    },
    {
      "name": "spring.ai.alibaba.mcp.nacos.registry.sse-export-context-path",
      "type": "java.lang.String",
      "description": "base context path for sse mcp server.",
      "defaultValue": ""
    }
  ],
  "hints": []
}
